[{"name": "sony", "price": 1455, "img": "https://yandex.ru/images/search?text=%D0%A2%D0%B5%D0%BB%D0%B5%D0%B2%D0%B8%D0%B7%D0%BE%D1%80&isize=small&type=clipart&itype=jpg&from=tabbar&pos=0&rpt=simage&img_url=https%3A%2F%2Fcdn.rbt.ru%2Fimages%2Fitem%2Fimage%2F614%2F613043_647375940_24ae10ee78f5cce408f9efb549108ae0.jpg"}, {"name": "Xiaomi", "price": 2000, "img": "https://yandex.ru/images/search?text=%D0%A2%D0%B5%D0%BB%D0%B5%D0%B2%D0%B8%D0%B7%D0%BE%D1%80&isize=small&type=clipart&itype=jpg&from=tabbar&pos=0&rpt=simage&img_url=https%3A%2F%2Fcdn.rbt.ru%2Fimages%2Fitem%2Fimage%2F614%2F613043_647375940_24ae10ee78f5cce408f9efb549108ae0.jpg"}, {"name": "LG", "price": 3000, "img": "https://yandex.ru/images/search?text=%D0%A2%D0%B5%D0%BB%D0%B5%D0%B2%D0%B8%D0%B7%D0%BE%D1%80&isize=small&type=clipart&itype=jpg&from=tabbar&pos=0&rpt=simage&img_url=https%3A%2F%2Fcdn.rbt.ru%2Fimages%2Fitem%2Fimage%2F614%2F613043_647375940_24ae10ee78f5cce408f9efb549108ae0.jpg"}]